markdown/serializers.py
markdown/__main__.py
markdown/preprocessors.py
markdown/postprocessors.py
markdown/blockparser.py
markdown/__version__.py
markdown/__init__.py
markdown/blockprocessors.py
markdown/odict.py
markdown/inlinepatterns.py
markdown/util.py
markdown/treeprocessors.py
markdown/extensions/smarty.py
markdown/extensions/fenced_code.py
markdown/extensions/codehilite.py
markdown/extensions/abbr.py
markdown/extensions/extra.py
markdown/extensions/__init__.py
markdown/extensions/meta.py
markdown/extensions/footnotes.py
markdown/extensions/attr_list.py
markdown/extensions/tables.py
markdown/extensions/headerid.py
markdown/extensions/def_list.py
markdown/extensions/toc.py
markdown/extensions/admonition.py
markdown/extensions/wikilinks.py
markdown/extensions/nl2br.py
markdown/extensions/sane_lists.py
markdown/extensions/smart_strong.py
markdown_py26_support-2.6.2.dist-info/metadata.json
markdown_py26_support-2.6.2.dist-info/DESCRIPTION.rst
markdown_py26_support-2.6.2.dist-info/METADATA
markdown_py26_support-2.6.2.dist-info/top_level.txt
markdown_py26_support-2.6.2.dist-info/WHEEL
markdown_py26_support-2.6.2.dist-info/RECORD
